ovos_tts_plugin_mimic/__init__.py
ovos_tts_plugin_mimic/version.py
ovos_tts_plugin_mimic-0.3.0.dist-info/LICENSE
ovos_tts_plugin_mimic-0.3.0.dist-info/METADATA
ovos_tts_plugin_mimic-0.3.0.dist-info/WHEEL
ovos_tts_plugin_mimic-0.3.0.dist-info/entry_points.txt
ovos_tts_plugin_mimic-0.3.0.dist-info/top_level.txt
ovos_tts_plugin_mimic-0.3.0.dist-info/zip-safe
ovos_tts_plugin_mimic-0.3.0.dist-info/RECORD
